pydeepsee/__init__.py
pydeepsee/cli.py
pydeepsee/contrast.py
pydeepsee/dehaze.py
pydeepsee/filters.py
pydeepsee-0.1.4.dist-info/METADATA
pydeepsee-0.1.4.dist-info/WHEEL
pydeepsee-0.1.4.dist-info/top_level.txt
pydeepsee-0.1.4.dist-info/RECORD
