Metadata-Version: 2.4
Name: pydeepsee
Version: 0.1.4
Requires-Dist: opencv-python>=4.5.0
Requires-Dist: numpy>=1.21.0
Dynamic: description
Dynamic: description-content-type
Dynamic: requires-dist
